labylib/Cape.py
labylib/Hat.py
labylib/__init__.py
labylib-0.2.0.dist-info/LICENSE
labylib-0.2.0.dist-info/METADATA
labylib-0.2.0.dist-info/WHEEL
labylib-0.2.0.dist-info/top_level.txt
labylib-0.2.0.dist-info/RECORD
