Metadata-Version: 2.1
Name: labylib
Version: 0.2.0
Summary: API to modify LabyMod cosmetics
Home-page: https://github.com/VictorWesterlund/labylib
Author: VicW
Author-email: victor.vesterlund@gmail.com
License: UNKNOWN
Platform: UNKNOWN
Classifier: Programming Language :: Python :: 3
Classifier: License :: OSI Approved :: MIT License
Classifier: Operating System :: OS Independent
Requires-Python: >=3.6
